[{"win": 0, "gameId": 1053905, "firstBaron": 0, "towerKills": [10, 1], "baronKills": [1, 0], "players": [{"firstBloodInvolve": false, "name": "JT Rest", "champId": 6, "firstDeath": false}, {"firstBloodInvolve": true, "name": "JT Hana", "champId": 64, "firstDeath": false}, {"firstBloodInvolve": true, "name": "JT FoFo", "champId": 134, "firstDeath": false}, {"firstBloodInvolve": false, "name": "JT Lilv", "champId": 236, "firstDeath": false}, {"firstBloodInvolve": true, "name": "JT Koala", "champId": 79, "firstDeath": false}, {"firstBloodInvolve": false, "name": "DG 2188", "champId": 14, "firstDeath": false}, {"firstBloodInvolve": false, "name": "DG JGY", "champId": 5, "firstDeath": true}, {"firstBloodInvolve": false, "name": "DG Moonblack", "champId": 7, "firstDeath": false}, {"firstBloodInvolve": false, "name": "DG YuLun", "champId": 145, "firstDeath": false}, {"firstBloodInvolve": false, "name": "DG pasa", "champId": 12, "firstDeath": false}], "bans": [[76, 142, 201, 13, 266], [69, 127, 84, 39, 517]], "duration": 1502, "firstBlood": 0, "patch": "9.2", "firstRiftHerald": 0, "firstInhibitor": 0, "firstDragon": 1, "teamNames": ["JT", "DG"], "inhibitorKills": [2, 0], "dragonKills": [0, 2], "firstTower": 1, "time": 1550236006861}, {"win": 1, "gameId": 1053892, "firstBaron": false, "towerKills": [0, 10], "baronKills": [0, 0], "players": [{"firstBloodInvolve": false, "name": "DG 2188", "champId": 126, "firstDeath": false}, {"firstBloodInvolve": false, "name": "DG JGY", "champId": 203, "firstDeath": true}, {"firstBloodInvolve": false, "name": "DG Moonblack", "champId": 117, "firstDeath": false}, {"firstBloodInvolve": false, "name": "DG YuLun", "champId": 145, "firstDeath": false}, {"firstBloodInvolve": false, "name": "DG pasa", "champId": 12, "firstDeath": false}, {"firstBloodInvolve": false, "name": "JT Rest", "champId": 83, "firstDeath": false}, {"firstBloodInvolve": true, "name": "JT Hana", "champId": 64, "firstDeath": false}, {"firstBloodInvolve": false, "name": "JT FoFo", "champId": 84, "firstDeath": false}, {"firstBloodInvolve": true, "name": "JT Lilv", "champId": 81, "firstDeath": false}, {"firstBloodInvolve": false, "name": "JT Koala", "champId": 223, "firstDeath": false}], "bans": [[14, 127, 39, 142, 517], [236, 76, 69, 6, 7]], "duration": 1528, "firstBlood": 1, "patch": "9.2", "firstRiftHerald": 1, "firstInhibitor": 1, "firstDragon": 1, "teamNames": ["DG", "JT"], "inhibitorKills": [0, 2], "dragonKills": [0, 2], "firstTower": 1, "time": 1550231150863}, {"win": 1, "gameId": 1053890, "firstBaron": false, "towerKills": [6, 8], "baronKills": [0, 2], "players": [{"firstBloodInvolve": false, "name": "GRX PK", "champId": 517, "firstDeath": false}, {"firstBloodInvolve": true, "name": "GRX Raise", "champId": 154, "firstDeath": false}, {"firstBloodInvolve": false, "name": "GRX Wuji", "champId": 14, "firstDeath": false}, {"firstBloodInvolve": true, "name": "GRX Bruce", "champId": 498, "firstDeath": false}, {"firstBloodInvolve": true, "name": "GRX Yoon", "champId": 497, "firstDeath": false}, {"firstBloodInvolve": false, "name": "MAD Rock", "champId": 6, "firstDeath": false}, {"firstBloodInvolve": false, "name": "MAD Kongyue", "champId": 266, "firstDeath": false}, {"firstBloodInvolve": false, "name": "MAD Uniboy", "champId": 127, "firstDeath": false}, {"firstBloodInvolve": false, "name": "MAD Breeze", "champId": 145, "firstDeath": true}, {"firstBloodInvolve": false, "name": "MAD K", "champId": 201, "firstDeath": false}], "bans": [[142, 2, 81, 79, 113], [69, 83, 236, 12, 412]], "duration": 2199, "firstBlood": 0, "patch": "9.2", "firstRiftHerald": 0, "firstInhibitor": 1, "firstDragon": 0, "teamNames": ["GRX", "MAD"], "inhibitorKills": [0, 1], "dragonKills": [3, 2], "firstTower": 0, "time": 1550227384249}, {"win": 1, "gameId": 1053889, "firstBaron": false, "towerKills": [0, 9], "baronKills": [0, 1], "players": [{"firstBloodInvolve": false, "name": "MAD Rock", "champId": 6, "firstDeath": false}, {"firstBloodInvolve": true, "name": "MAD Kongyue", "champId": 64, "firstDeath": false}, {"firstBloodInvolve": false, "name": "MAD Uniboy", "champId": 3, "firstDeath": false}, {"firstBloodInvolve": true, "name": "MAD Breeze", "champId": 15, "firstDeath": false}, {"firstBloodInvolve": true, "name": "MAD K", "champId": 223, "firstDeath": false}, {"firstBloodInvolve": false, "name": "GRX PK", "champId": 83, "firstDeath": false}, {"firstBloodInvolve": false, "name": "GRX Raise", "champId": 154, "firstDeath": false}, {"firstBloodInvolve": false, "name": "GRX Wuji", "champId": 14, "firstDeath": false}, {"firstBloodInvolve": false, "name": "GRX Bruce", "champId": 145, "firstDeath": true}, {"firstBloodInvolve": false, "name": "GRX Yoon", "champId": 79, "firstDeath": false}], "bans": [[236, 517, 127, 201, 12], [69, 142, 81, 2, 113]], "duration": 1955, "firstBlood": 0, "patch": "9.2", "firstRiftHerald": 0, "firstInhibitor": 1, "firstDragon": 0, "teamNames": ["MAD", "GRX"], "inhibitorKills": [0, 1], "dragonKills": [1, 2], "firstTower": 1, "time": 1550223643632}, {"win": 1, "gameId": 1053887, "firstBaron": false, "towerKills": [3, 8], "baronKills": [0, 1], "players": [{"firstBloodInvolve": false, "name": "GRX PK", "champId": 266, "firstDeath": false}, {"firstBloodInvolve": true, "name": "GRX Raise", "champId": 154, "firstDeath": false}, {"firstBloodInvolve": true, "name": "GRX Wuji", "champId": 127, "firstDeath": false}, {"firstBloodInvolve": false, "name": "GRX Bruce", "champId": 236, "firstDeath": false}, {"firstBloodInvolve": true, "name": "GRX Yoon", "champId": 201, "firstDeath": false}, {"firstBloodInvolve": false, "name": "MAD Rock", "champId": 6, "firstDeath": false}, {"firstBloodInvolve": false, "name": "MAD Kongyue", "champId": 79, "firstDeath": true}, {"firstBloodInvolve": false, "name": "MAD Uniboy", "champId": 14, "firstDeath": false}, {"firstBloodInvolve": false, "name": "MAD Breeze", "champId": 81, "firstDeath": false}, {"firstBloodInvolve": false, "name": "MAD K", "champId": 412, "firstDeath": false}], "bans": [[142, 3, 2, 134, 84], [69, 517, 223, 83, 72]], "duration": 2006, "firstBlood": 0, "patch": "9.2", "firstRiftHerald": 0, "firstInhibitor": 1, "firstDragon": 0, "teamNames": ["GRX", "MAD"], "inhibitorKills": [0, 1], "dragonKills": [2, 1], "firstTower": 0, "time": 1550220226534}, {"win": 1, "gameId": 1053822, "firstBaron": false, "towerKills": [0, 10], "baronKills": [1, 1], "players": [{"firstBloodInvolve": true, "name": "HKA 3z", "champId": 14, "firstDeath": false}, {"firstBloodInvolve": true, "name": "HKA Gemini", "champId": 164, "firstDeath": false}, {"firstBloodInvolve": false, "name": "HKA M1ssion", "champId": 127, "firstDeath": false}, {"firstBloodInvolve": false, "name": "HKA Unified", "champId": 145, "firstDeath": false}, {"firstBloodInvolve": false, "name": "HKA Kaiwing", "champId": 111, "firstDeath": false}, {"firstBloodInvolve": false, "name": "JT Rest", "champId": 6, "firstDeath": true}, {"firstBloodInvolve": false, "name": "JT Hana", "champId": 2, "firstDeath": false}, {"firstBloodInvolve": false, "name": "JT FoFo", "champId": 517, "firstDeath": false}, {"firstBloodInvolve": false, "name": "JT Lilv", "champId": 81, "firstDeath": false}, {"firstBloodInvolve": false, "name": "JT Koala", "champId": 223, "firstDeath": false}], "bans": [[84, 12, 69, 154, 83], [236, 142, 126, 201, 497]], "duration": 2346, "firstBlood": 0, "patch": "9.2", "firstRiftHerald": 1, "firstInhibitor": 1, "firstDragon": 1, "teamNames": ["HKA", "JT"], "inhibitorKills": [0, 2], "dragonKills": [1, 4], "firstTower": 1, "time": 1550157781444}, {"win": 0, "gameId": 1053819, "firstBaron": 0, "towerKills": [9, 2], "baronKills": [1, 0], "players": [{"firstBloodInvolve": false, "name": "HKA 3z", "champId": 14, "firstDeath": false}, {"firstBloodInvolve": false, "name": "HKA Gemini", "champId": 60, "firstDeath": true}, {"firstBloodInvolve": false, "name": "HKA M1ssion", "champId": 126, "firstDeath": false}, {"firstBloodInvolve": false, "name": "HKA MnM", "champId": 110, "firstDeath": false}, {"firstBloodInvolve": false, "name": "HKA Kaiwing", "champId": 201, "firstDeath": false}, {"firstBloodInvolve": true, "name": "JT Rest", "champId": 266, "firstDeath": false}, {"firstBloodInvolve": false, "name": "JT Hana", "champId": 56, "firstDeath": false}, {"firstBloodInvolve": true, "name": "JT FoFo", "champId": 517, "firstDeath": false}, {"firstBloodInvolve": false, "name": "JT Lilv", "champId": 145, "firstDeath": false}, {"firstBloodInvolve": false, "name": "JT Koala", "champId": 12, "firstDeath": false}], "bans": [[223, 84, 69, 154, 83], [236, 142, 164, 13, 7]], "duration": 1867, "firstBlood": 1, "patch": "9.2", "firstRiftHerald": 0, "firstInhibitor": 0, "firstDragon": 0, "teamNames": ["HKA", "JT"], "inhibitorKills": [1, 0], "dragonKills": [3, 1], "firstTower": 0, "time": 1550153344890}, {"win": 0, "gameId": 1053800, "firstBaron": false, "towerKills": [8, 11], "baronKills": [2, 2], "players": [{"firstBloodInvolve": false, "name": "JT Rest", "champId": 6, "firstDeath": false}, {"firstBloodInvolve": false, "name": "JT Hana", "champId": 2, "firstDeath": false}, {"firstBloodInvolve": false, "name": "JT FoFo", "champId": 134, "firstDeath": true}, {"firstBloodInvolve": false, "name": "JT Lilv", "champId": 15, "firstDeath": false}, {"firstBloodInvolve": false, "name": "JT Koala", "champId": 12, "firstDeath": false}, {"firstBloodInvolve": false, "name": "HKA 3z", "champId": 83, "firstDeath": false}, {"firstBloodInvolve": true, "name": "HKA Gemini", "champId": 64, "firstDeath": false}, {"firstBloodInvolve": true, "name": "HKA M1ssion", "champId": 142, "firstDeath": false}, {"firstBloodInvolve": false, "name": "HKA Unified", "champId": 145, "firstDeath": false}, {"firstBloodInvolve": false, "name": "HKA Kaiwing", "champId": 201, "firstDeath": false}], "bans": [[127, 81, 164, 126, 14], [69, 84, 236, 7, 13]], "duration": 3100, "firstBlood": 1, "patch": "9.2", "firstRiftHerald": 0, "firstInhibitor": 1, "firstDragon": 1, "teamNames": ["JT", "HKA"], "inhibitorKills": [1, 5], "dragonKills": [3, 4], "firstTower": 0, "time": 1550147671333}, {"win": 0, "gameId": 1053796, "firstBaron": 0, "towerKills": [10, 0], "baronKills": [1, 0], "players": [{"firstBloodInvolve": false, "name": "MAD Rock", "champId": 14, "firstDeath": true}, {"firstBloodInvolve": false, "name": "MAD Kongyue", "champId": 64, "firstDeath": false}, {"firstBloodInvolve": false, "name": "MAD Uniboy", "champId": 127, "firstDeath": false}, {"firstBloodInvolve": false, "name": "MAD Breeze", "champId": 81, "firstDeath": false}, {"firstBloodInvolve": false, "name": "MAD K", "champId": 223, "firstDeath": false}, {"firstBloodInvolve": true, "name": "ALF Leaky", "champId": 6, "firstDeath": false}, {"firstBloodInvolve": true, "name": "ALF WSY", "champId": 56, "firstDeath": false}, {"firstBloodInvolve": false, "name": "ALF Caipi", "champId": 3, "firstDeath": false}, {"firstBloodInvolve": false, "name": "ALF Xiaoemo", "champId": 15, "firstDeath": false}, {"firstBloodInvolve": false, "name": "ALF SkuLL", "champId": 201, "firstDeath": false}], "bans": [[236, 164, 59, 145, 412], [84, 517, 69, 79, 154]], "duration": 1653, "firstBlood": 1, "patch": "9.2", "firstRiftHerald": 0, "firstInhibitor": 0, "firstDragon": 0, "teamNames": ["MAD", "ALF"], "inhibitorKills": [2, 0], "dragonKills": [2, 0], "firstTower": 0, "time": 1550143996341}, {"win": 0, "gameId": 1053795, "firstBaron": 0, "towerKills": [10, 2], "baronKills": [2, 0], "players": [{"firstBloodInvolve": false, "name": "MAD Rock", "champId": 266, "firstDeath": true}, {"firstBloodInvolve": false, "name": "MAD Kongyue", "champId": 154, "firstDeath": false}, {"firstBloodInvolve": false, "name": "MAD Uniboy", "champId": 69, "firstDeath": false}, {"firstBloodInvolve": false, "name": "MAD Breeze", "champId": 15, "firstDeath": false}, {"firstBloodInvolve": false, "name": "MAD K", "champId": 223, "firstDeath": false}, {"firstBloodInvolve": true, "name": "ALF Leaky", "champId": 6, "firstDeath": false}, {"firstBloodInvolve": true, "name": "ALF WSY", "champId": 121, "firstDeath": false}, {"firstBloodInvolve": false, "name": "ALF Caipi", "champId": 127, "firstDeath": false}, {"firstBloodInvolve": false, "name": "ALF Xiaoemo", "champId": 145, "firstDeath": false}, {"firstBloodInvolve": false, "name": "ALF SkuLL", "champId": 201, "firstDeath": false}], "bans": [[236, 164, 59, 3, 142], [84, 517, 81, 8, 79]], "duration": 2260, "firstBlood": 1, "patch": "9.2", "firstRiftHerald": 0, "firstInhibitor": 0, "firstDragon": 0, "teamNames": ["MAD", "ALF"], "inhibitorKills": [2, 0], "dragonKills": [3, 2], "firstTower": 0, "time": 1550139950271}, {"win": 1, "gameId": 1053794, "firstBaron": false, "towerKills": [4, 11], "baronKills": [1, 2], "players": [{"firstBloodInvolve": false, "name": "MAD Rock", "champId": 14, "firstDeath": false}, {"firstBloodInvolve": true, "name": "MAD Kongyue", "champId": 5, "firstDeath": false}, {"firstBloodInvolve": false, "name": "MAD Uniboy", "champId": 69, "firstDeath": false}, {"firstBloodInvolve": true, "name": "MAD Breeze", "champId": 51, "firstDeath": false}, {"firstBloodInvolve": true, "name": "MAD K", "champId": 25, "firstDeath": false}, {"firstBloodInvolve": false, "name": "ALF Leaky", "champId": 6, "firstDeath": false}, {"firstBloodInvolve": false, "name": "ALF WSY", "champId": 59, "firstDeath": false}, {"firstBloodInvolve": false, "name": "ALF Caipi", "champId": 7, "firstDeath": false}, {"firstBloodInvolve": false, "name": "ALF Xiaoemo", "champId": 145, "firstDeath": true}, {"firstBloodInvolve": false, "name": "ALF SkuLL", "champId": 16, "firstDeath": false}], "bans": [[236, 164, 67, 3, 142], [84, 517, 81, 79, 8]], "duration": 2569, "firstBlood": 0, "patch": "9.2", "firstRiftHerald": 1, "firstInhibitor": 1, "firstDragon": 0, "teamNames": ["MAD", "ALF"], "inhibitorKills": [0, 3], "dragonKills": [1, 4], "firstTower": 1, "time": 1550135878061}, {"win": 1, "gameId": 1000687, "firstBaron": 0, "towerKills": [8, 7], "baronKills": [1, 1], "players": [{"firstBloodInvolve": false, "name": "ALF Leaky", "champId": 266, "firstDeath": false}, {"firstBloodInvolve": true, "name": "ALF WSY", "champId": 164, "firstDeath": false}, {"firstBloodInvolve": false, "name": "ALF Caipi", "champId": 3, "firstDeath": false}, {"firstBloodInvolve": true, "name": "ALF Xiaoemo", "champId": 15, "firstDeath": false}, {"firstBloodInvolve": true, "name": "ALF SkuLL", "champId": 412, "firstDeath": false}, {"firstBloodInvolve": false, "name": "HKA 3z", "champId": 6, "firstDeath": false}, {"firstBloodInvolve": false, "name": "HKA Crash", "champId": 5, "firstDeath": false}, {"firstBloodInvolve": false, "name": "HKA M1ssion", "champId": 127, "firstDeath": false}, {"firstBloodInvolve": false, "name": "HKA Unified", "champId": 145, "firstDeath": true}, {"firstBloodInvolve": false, "name": "HKA Kaiwing", "champId": 201, "firstDeath": false}], "bans": [[497, 30, 142, 12, 64], [69, 7, 236, 110, 223]], "duration": 2220, "firstBlood": 0, "patch": "9.1", "firstRiftHerald": 0, "firstInhibitor": 0, "firstDragon": 1, "teamNames": ["ALF", "HKA"], "inhibitorKills": [1, 1], "dragonKills": [1, 4], "firstTower": 1, "time": 1548508645657}, {"win": 0, "gameId": 982399, "firstBaron": 0, "towerKills": [11, 3], "baronKills": [2, 0], "players": [{"firstBloodInvolve": true, "name": "HKA 3z", "champId": 14, "firstDeath": false}, {"firstBloodInvolve": true, "name": "HKA Crash", "champId": 64, "firstDeath": false}, {"firstBloodInvolve": false, "name": "HKA M1ssion", "champId": 3, "firstDeath": false}, {"firstBloodInvolve": false, "name": "HKA Unified", "champId": 145, "firstDeath": false}, {"firstBloodInvolve": false, "name": "HKA Kaiwing", "champId": 201, "firstDeath": false}, {"firstBloodInvolve": false, "name": "ALF Leaky", "champId": 24, "firstDeath": true}, {"firstBloodInvolve": false, "name": "ALF WSY", "champId": 79, "firstDeath": false}, {"firstBloodInvolve": false, "name": "ALF Caipi", "champId": 39, "firstDeath": false}, {"firstBloodInvolve": false, "name": "ALF Xiaoemo", "champId": 498, "firstDeath": false}, {"firstBloodInvolve": false, "name": "ALF SkuLL", "champId": 497, "firstDeath": false}], "bans": [[236, 223, 6, 113, 8], [266, 69, 127, 164, 56]], "duration": 1835, "firstBlood": 0, "patch": "9.1", "firstRiftHerald": 0, "firstInhibitor": 0, "firstDragon": 0, "teamNames": ["HKA", "ALF"], "inhibitorKills": [2, 0], "dragonKills": [5, 0], "firstTower": 0, "time": 1548503843955}, {"win": 1, "gameId": 992526, "firstBaron": false, "towerKills": [3, 10], "baronKills": [0, 2], "players": [{"firstBloodInvolve": false, "name": "DG 2188", "champId": 58, "firstDeath": false}, {"firstBloodInvolve": true, "name": "DG JGY", "champId": 76, "firstDeath": false}, {"firstBloodInvolve": false, "name": "DG Moonblack", "champId": 3, "firstDeath": false}, {"firstBloodInvolve": false, "name": "DG Xiaobo", "champId": 81, "firstDeath": false}, {"firstBloodInvolve": false, "name": "DG pasa", "champId": 412, "firstDeath": false}, {"firstBloodInvolve": false, "name": "GRX PK", "champId": 78, "firstDeath": false}, {"firstBloodInvolve": false, "name": "GRX Raise", "champId": 121, "firstDeath": true}, {"firstBloodInvolve": false, "name": "GRX Wuji", "champId": 127, "firstDeath": false}, {"firstBloodInvolve": false, "name": "GRX Bruce", "champId": 145, "firstDeath": false}, {"firstBloodInvolve": false, "name": "GRX Yoon", "champId": 12, "firstDeath": false}], "bans": [[497, 39, 14, 5, 56], [69, 266, 6, 25, 223]], "duration": 1919, "firstBlood": 0, "patch": "9.1", "firstRiftHerald": 0, "firstInhibitor": 1, "firstDragon": 1, "teamNames": ["DG", "GRX"], "inhibitorKills": [0, 2], "dragonKills": [0, 3], "firstTower": 1, "time": 1548499922517}, {"win": 0, "gameId": 1010622, "firstBaron": false, "towerKills": [8, 1], "baronKills": [0, 0], "players": [{"firstBloodInvolve": false, "name": "DG 2188", "champId": 6, "firstDeath": false}, {"firstBloodInvolve": false, "name": "DG JGY", "champId": 76, "firstDeath": false}, {"firstBloodInvolve": false, "name": "DG Moonblack", "champId": 105, "firstDeath": false}, {"firstBloodInvolve": false, "name": "DG Xiaobo", "champId": 81, "firstDeath": true}, {"firstBloodInvolve": false, "name": "DG pasa", "champId": 12, "firstDeath": false}, {"firstBloodInvolve": false, "name": "GRX PK", "champId": 266, "firstDeath": false}, {"firstBloodInvolve": false, "name": "GRX Raise", "champId": 72, "firstDeath": false}, {"firstBloodInvolve": false, "name": "GRX Wuji", "champId": 13, "firstDeath": false}, {"firstBloodInvolve": true, "name": "GRX Bruce", "champId": 145, "firstDeath": false}, {"firstBloodInvolve": true, "name": "GRX Yoon", "champId": 201, "firstDeath": false}], "bans": [[497, 14, 39, 127, 84], [69, 3, 7, 117, 142]], "duration": 1474, "firstBlood": 1, "patch": "9.1", "firstRiftHerald": 0, "firstInhibitor": 0, "firstDragon": 1, "teamNames": ["DG", "GRX"], "inhibitorKills": [1, 0], "dragonKills": [1, 1], "firstTower": 0, "time": 1548496523842}, {"win": 1, "gameId": 982306, "firstBaron": false, "towerKills": [3, 9], "baronKills": [0, 1], "players": [{"firstBloodInvolve": false, "name": "DG 2188", "champId": 68, "firstDeath": false}, {"firstBloodInvolve": true, "name": "DG JGY", "champId": 64, "firstDeath": false}, {"firstBloodInvolve": true, "name": "DG Moonblack", "champId": 7, "firstDeath": false}, {"firstBloodInvolve": false, "name": "DG Xiaobo", "champId": 236, "firstDeath": false}, {"firstBloodInvolve": false, "name": "DG pasa", "champId": 201, "firstDeath": false}, {"firstBloodInvolve": false, "name": "GRX PK", "champId": 13, "firstDeath": false}, {"firstBloodInvolve": false, "name": "GRX Raise", "champId": 79, "firstDeath": false}, {"firstBloodInvolve": false, "name": "GRX Wuji", "champId": 14, "firstDeath": true}, {"firstBloodInvolve": false, "name": "GRX Bruce", "champId": 498, "firstDeath": false}, {"firstBloodInvolve": false, "name": "GRX Yoon", "champId": 497, "firstDeath": false}], "bans": [[127, 39, 266, 164, 56], [69, 3, 6, 412, 25]], "duration": 2050, "firstBlood": 0, "patch": "9.1", "firstRiftHerald": 0, "firstInhibitor": 1, "firstDragon": 0, "teamNames": ["DG", "GRX"], "inhibitorKills": [0, 2], "dragonKills": [1, 4], "firstTower": 1, "time": 1548492296548}, {"win": 0, "gameId": 981988, "firstBaron": 0, "towerKills": [9, 1], "baronKills": [1, 0], "players": [{"firstBloodInvolve": false, "name": "ALF Leaky", "champId": 6, "firstDeath": false}, {"firstBloodInvolve": true, "name": "ALF WSY", "champId": 164, "firstDeath": false}, {"firstBloodInvolve": true, "name": "ALF Caipi", "champId": 3, "firstDeath": false}, {"firstBloodInvolve": false, "name": "ALF Xiaoemo", "champId": 145, "firstDeath": false}, {"firstBloodInvolve": false, "name": "ALF SkuLL", "champId": 201, "firstDeath": false}, {"firstBloodInvolve": false, "name": "JT Rest", "champId": 67, "firstDeath": false}, {"firstBloodInvolve": false, "name": "JT Hana", "champId": 5, "firstDeath": false}, {"firstBloodInvolve": false, "name": "JT FoFo", "champId": 14, "firstDeath": true}, {"firstBloodInvolve": false, "name": "JT Lilv", "champId": 81, "firstDeath": false}, {"firstBloodInvolve": false, "name": "JT Koala", "champId": 12, "firstDeath": false}], "bans": [[84, 497, 266, 8, 142], [69, 236, 121, 25, 223]], "duration": 1680, "firstBlood": 0, "patch": "9.1", "firstRiftHerald": 1, "firstInhibitor": 0, "firstDragon": 0, "teamNames": ["ALF", "JT"], "inhibitorKills": [1, 0], "dragonKills": [3, 0], "firstTower": 0, "time": 1548428200879}, {"win": 0, "gameId": 1000596, "firstBaron": 0, "towerKills": [11, 3], "baronKills": [2, 0], "players": [{"firstBloodInvolve": false, "name": "JT Rest", "champId": 6, "firstDeath": false}, {"firstBloodInvolve": false, "name": "JT Hana", "champId": 154, "firstDeath": false}, {"firstBloodInvolve": false, "name": "JT FoFo", "champId": 266, "firstDeath": false}, {"firstBloodInvolve": false, "name": "JT Lilv", "champId": 112, "firstDeath": false}, {"firstBloodInvolve": false, "name": "JT Koala", "champId": 412, "firstDeath": true}, {"firstBloodInvolve": false, "name": "ALF Leaky", "champId": 14, "firstDeath": false}, {"firstBloodInvolve": true, "name": "ALF WSY", "champId": 2, "firstDeath": false}, {"firstBloodInvolve": true, "name": "ALF Caipi", "champId": 127, "firstDeath": false}, {"firstBloodInvolve": false, "name": "ALF Xiaoemo", "champId": 22, "firstDeath": false}, {"firstBloodInvolve": true, "name": "ALF SkuLL", "champId": 223, "firstDeath": false}], "bans": [[39, 236, 121, 81, 110], [69, 497, 84, 79, 15]], "duration": 2644, "firstBlood": 1, "patch": "9.1", "firstRiftHerald": 0, "firstInhibitor": 0, "firstDragon": 1, "teamNames": ["JT", "ALF"], "inhibitorKills": [3, 0], "dragonKills": [1, 6], "firstTower": 1, "time": 1548423170674}, {"win": 1, "gameId": 992016, "firstBaron": 0, "towerKills": [4, 7], "baronKills": [1, 1], "players": [{"firstBloodInvolve": false, "name": "JT Rest", "champId": 266, "firstDeath": false}, {"firstBloodInvolve": true, "name": "JT Breaker", "champId": 113, "firstDeath": false}, {"firstBloodInvolve": true, "name": "JT FoFo", "champId": 14, "firstDeath": false}, {"firstBloodInvolve": true, "name": "JT Lilv", "champId": 81, "firstDeath": false}, {"firstBloodInvolve": true, "name": "JT Koala", "champId": 223, "firstDeath": false}, {"firstBloodInvolve": false, "name": "ALF Leaky", "champId": 6, "firstDeath": false}, {"firstBloodInvolve": false, "name": "ALF WSY", "champId": 121, "firstDeath": false}, {"firstBloodInvolve": false, "name": "ALF Caipi", "champId": 7, "firstDeath": false}, {"firstBloodInvolve": false, "name": "ALF Xiaoemo", "champId": 236, "firstDeath": false}, {"firstBloodInvolve": false, "name": "ALF SkuLL", "champId": 201, "firstDeath": true}], "bans": [[39, 3, 127, 142, 79], [69, 84, 497, 154, 64]], "duration": 2254, "firstBlood": 0, "patch": "9.1", "firstRiftHerald": 1, "firstInhibitor": 1, "firstDragon": 0, "teamNames": ["JT", "ALF"], "inhibitorKills": [0, 1], "dragonKills": [1, 3], "firstTower": 0, "time": 1548418239390}, {"win": 0, "gameId": 991993, "firstBaron": 0, "towerKills": [6, 3], "baronKills": [1, 0], "players": [{"firstBloodInvolve": false, "name": "AHQ Ziv", "champId": 240, "firstDeath": false}, {"firstBloodInvolve": false, "name": "AHQ Alex", "champId": 113, "firstDeath": false}, {"firstBloodInvolve": false, "name": "AHQ Wako", "champId": 127, "firstDeath": false}, {"firstBloodInvolve": true, "name": "AHQ An", "champId": 145, "firstDeath": false}, {"firstBloodInvolve": true, "name": "AHQ Kino", "champId": 12, "firstDeath": false}, {"firstBloodInvolve": false, "name": "GRX PK", "champId": 6, "firstDeath": false}, {"firstBloodInvolve": false, "name": "GRX Raise", "champId": 154, "firstDeath": false}, {"firstBloodInvolve": false, "name": "GRX Wuji", "champId": 14, "firstDeath": false}, {"firstBloodInvolve": false, "name": "GRX Bruce", "champId": 112, "firstDeath": false}, {"firstBloodInvolve": false, "name": "GRX Yoon", "champId": 412, "firstDeath": true}], "bans": [[497, 236, 121, 223, 25], [69, 266, 3, 8, 122]], "duration": 1648, "firstBlood": 0, "patch": "9.1", "firstRiftHerald": 0, "firstInhibitor": 0, "firstDragon": 0, "teamNames": ["AHQ", "GRX"], "inhibitorKills": [1, 0], "dragonKills": [2, 1], "firstTower": 0, "time": 1548414826036}, {"win": 0, "gameId": 1000552, "firstBaron": 0, "towerKills": [11, 1], "baronKills": [2, 0], "players": [{"firstBloodInvolve": false, "name": "GRX PK", "champId": 6, "firstDeath": false}, {"firstBloodInvolve": true, "name": "GRX Raise", "champId": 121, "firstDeath": false}, {"firstBloodInvolve": true, "name": "GRX Wuji", "champId": 127, "firstDeath": false}, {"firstBloodInvolve": true, "name": "GRX Bruce", "champId": 145, "firstDeath": false}, {"firstBloodInvolve": true, "name": "GRX Yoon", "champId": 412, "firstDeath": false}, {"firstBloodInvolve": false, "name": "AHQ Ziv", "champId": 112, "firstDeath": false}, {"firstBloodInvolve": false, "name": "AHQ Alex", "champId": 164, "firstDeath": false}, {"firstBloodInvolve": false, "name": "AHQ Wako", "champId": 142, "firstDeath": false}, {"firstBloodInvolve": false, "name": "AHQ An", "champId": 236, "firstDeath": true}, {"firstBloodInvolve": false, "name": "AHQ Kino", "champId": 497, "firstDeath": false}], "bans": [[3, 84, 39, 14, 154], [69, 266, 12, 25]], "duration": 2596, "firstBlood": 0, "patch": "9.1", "firstRiftHerald": 0, "firstInhibitor": 0, "firstDragon": 0, "teamNames": ["GRX", "AHQ"], "inhibitorKills": [3, 0], "dragonKills": [6, 0], "firstTower": 0, "time": 1548409962085}, {"win": 0, "gameId": 991896, "firstBaron": 0, "towerKills": [11, 0], "baronKills": [1, 0], "players": [{"firstBloodInvolve": true, "name": "AHQ Ziv", "champId": 6, "firstDeath": false}, {"firstBloodInvolve": true, "name": "AHQ Alex", "champId": 154, "firstDeath": false}, {"firstBloodInvolve": false, "name": "AHQ Wako", "champId": 127, "firstDeath": false}, {"firstBloodInvolve": false, "name": "AHQ An", "champId": 81, "firstDeath": false}, {"firstBloodInvolve": false, "name": "AHQ Kino", "champId": 25, "firstDeath": false}, {"firstBloodInvolve": false, "name": "GRX PK", "champId": 122, "firstDeath": true}, {"firstBloodInvolve": false, "name": "GRX Raise", "champId": 121, "firstDeath": false}, {"firstBloodInvolve": false, "name": "GRX Wuji", "champId": 84, "firstDeath": false}, {"firstBloodInvolve": false, "name": "GRX Bruce", "champId": 236, "firstDeath": false}, {"firstBloodInvolve": false, "name": "GRX Yoon", "champId": 12, "firstDeath": false}], "bans": [[497, 164, 14, 142, 79], [69, 266, 3, 223, 5]], "duration": 1823, "firstBlood": 0, "patch": "9.1", "firstRiftHerald": 0, "firstInhibitor": 0, "firstDragon": 1, "teamNames": ["AHQ", "GRX"], "inhibitorKills": [3, 0], "dragonKills": [3, 1], "firstTower": 0, "time": 1548404939685}, {"win": 1, "gameId": 1033261, "firstBaron": false, "towerKills": [0, 10], "baronKills": [0, 1], "players": [{"firstBloodInvolve": false, "name": "MAD Liang", "champId": 6, "firstDeath": false}, {"firstBloodInvolve": false, "name": "MAD Kongyue", "champId": 121, "firstDeath": false}, {"firstBloodInvolve": false, "name": "MAD Uniboy", "champId": 134, "firstDeath": false}, {"firstBloodInvolve": false, "name": "MAD Breeze", "champId": 81, "firstDeath": true}, {"firstBloodInvolve": false, "name": "MAD K", "champId": 516, "firstDeath": false}, {"firstBloodInvolve": false, "name": "HKA 3z", "champId": 14, "firstDeath": false}, {"firstBloodInvolve": true, "name": "HKA Gemini", "champId": 164, "firstDeath": false}, {"firstBloodInvolve": false, "name": "HKA M1ssion", "champId": 142, "firstDeath": false}, {"firstBloodInvolve": true, "name": "HKA MnM", "champId": 145, "firstDeath": false}, {"firstBloodInvolve": true, "name": "HKA Kaiwing", "champId": 497, "firstDeath": false}], "bans": [[236, 127, 39, 412, 201], [69, 266, 3, 12, 223]], "duration": 1738, "firstBlood": 1, "patch": "9.1", "firstRiftHerald": 0, "firstInhibitor": 1, "firstDragon": 1, "teamNames": ["MAD", "HKA"], "inhibitorKills": [0, 1], "dragonKills": [0, 4], "firstTower": 1, "time": 1548336040652}, {"win": 0, "gameId": 991431, "firstBaron": 0, "towerKills": [10, 1], "baronKills": [1, 0], "players": [{"firstBloodInvolve": false, "name": "HKA 3z", "champId": 14, "firstDeath": false}, {"firstBloodInvolve": true, "name": "HKA Gemini", "champId": 5, "firstDeath": false}, {"firstBloodInvolve": true, "name": "HKA M1ssion", "champId": 127, "firstDeath": false}, {"firstBloodInvolve": true, "name": "HKA MnM", "champId": 110, "firstDeath": false}, {"firstBloodInvolve": true, "name": "HKA Kaiwing", "champId": 201, "firstDeath": false}, {"firstBloodInvolve": false, "name": "MAD Liang", "champId": 8, "firstDeath": false}, {"firstBloodInvolve": false, "name": "MAD Kongyue", "champId": 2, "firstDeath": false}, {"firstBloodInvolve": false, "name": "MAD Uniboy", "champId": 6, "firstDeath": false}, {"firstBloodInvolve": false, "name": "MAD Breeze", "champId": 145, "firstDeath": true}, {"firstBloodInvolve": false, "name": "MAD K", "champId": 516, "firstDeath": false}], "bans": [[81, 12, 3, 79, 497], [69, 266, 236, 223, 412]], "duration": 1713, "firstBlood": 0, "patch": "9.1", "firstRiftHerald": 1, "firstInhibitor": 0, "firstDragon": 0, "teamNames": ["HKA", "MAD"], "inhibitorKills": [2, 0], "dragonKills": [4, 0], "firstTower": 0, "time": 1548332796031}, {"win": 0, "gameId": 1033234, "firstBaron": 0, "towerKills": [9, 2], "baronKills": [1, 0], "players": [{"firstBloodInvolve": false, "name": "MAD Liang", "champId": 14, "firstDeath": false}, {"firstBloodInvolve": false, "name": "MAD Kongyue", "champId": 121, "firstDeath": false}, {"firstBloodInvolve": false, "name": "MAD Uniboy", "champId": 3, "firstDeath": false}, {"firstBloodInvolve": false, "name": "MAD Breeze", "champId": 145, "firstDeath": false}, {"firstBloodInvolve": false, "name": "MAD K", "champId": 12, "firstDeath": true}, {"firstBloodInvolve": false, "name": "HKA 3z", "champId": 126, "firstDeath": false}, {"firstBloodInvolve": true, "name": "HKA Crash", "champId": 30, "firstDeath": false}, {"firstBloodInvolve": true, "name": "HKA M1ssion", "champId": 127, "firstDeath": false}, {"firstBloodInvolve": true, "name": "HKA Unified", "champId": 81, "firstDeath": false}, {"firstBloodInvolve": true, "name": "HKA Kaiwing", "champId": 201, "firstDeath": false}], "bans": [[236, 39, 142, 84, 8], [266, 69, 6, 497, 412]], "duration": 1925, "firstBlood": 1, "patch": "9.1", "firstRiftHerald": 1, "firstInhibitor": 0, "firstDragon": 1, "teamNames": ["MAD", "HKA"], "inhibitorKills": [2, 0], "dragonKills": [2, 3], "firstTower": 1, "time": 1548327647774}, {"win": 1, "gameId": 991418, "firstBaron": false, "towerKills": [4, 7], "baronKills": [0, 1], "players": [{"firstBloodInvolve": false, "name": "DG 2188", "champId": 6, "firstDeath": false}, {"firstBloodInvolve": false, "name": "DG JGY", "champId": 76, "firstDeath": false}, {"firstBloodInvolve": false, "name": "DG Moonblack", "champId": 7, "firstDeath": false}, {"firstBloodInvolve": false, "name": "DG Xiaobo", "champId": 110, "firstDeath": true}, {"firstBloodInvolve": false, "name": "DG pasa", "champId": 201, "firstDeath": false}, {"firstBloodInvolve": false, "name": "FW Hanabi", "champId": 266, "firstDeath": false}, {"firstBloodInvolve": true, "name": "FW Bugi", "champId": 28, "firstDeath": false}, {"firstBloodInvolve": false, "name": "FW Rather", "champId": 14, "firstDeath": false}, {"firstBloodInvolve": true, "name": "FW Betty", "champId": 81, "firstDeath": false}, {"firstBloodInvolve": false, "name": "FW ShiauC", "champId": 223, "firstDeath": false}], "bans": [[84, 127, 39, 5, 164], [69, 3, 236, 79, 113]], "duration": 2374, "firstBlood": 1, "patch": "9.1", "firstRiftHerald": 1, "firstInhibitor": 1, "firstDragon": 0, "teamNames": ["DG", "FW"], "inhibitorKills": [0, 1], "dragonKills": [3, 1], "firstTower": 0, "time": 1548323538936}, {"win": 1, "gameId": 1033215, "firstBaron": false, "towerKills": [1, 10], "baronKills": [0, 2], "players": [{"firstBloodInvolve": false, "name": "DG 2188", "champId": 6, "firstDeath": false}, {"firstBloodInvolve": false, "name": "DG JGY", "champId": 203, "firstDeath": false}, {"firstBloodInvolve": false, "name": "DG Moonblack", "champId": 117, "firstDeath": false}, {"firstBloodInvolve": false, "name": "DG Xiaobo", "champId": 51, "firstDeath": true}, {"firstBloodInvolve": false, "name": "DG pasa", "champId": 25, "firstDeath": false}, {"firstBloodInvolve": false, "name": "FW Hanabi", "champId": 266, "firstDeath": false}, {"firstBloodInvolve": true, "name": "FW Bugi", "champId": 56, "firstDeath": false}, {"firstBloodInvolve": false, "name": "FW Rather", "champId": 127, "firstDeath": false}, {"firstBloodInvolve": true, "name": "FW Betty", "champId": 145, "firstDeath": false}, {"firstBloodInvolve": true, "name": "FW ShiauC", "champId": 12, "firstDeath": false}], "bans": [[84, 39, 5, 142, 164], [69, 3, 236, 223, 497]], "duration": 1845, "firstBlood": 1, "patch": "9.1", "firstRiftHerald": 1, "firstInhibitor": 1, "firstDragon": 1, "teamNames": ["DG", "FW"], "inhibitorKills": [0, 2], "dragonKills": [1, 3], "firstTower": 1, "time": 1548319254653}, {"win": 1, "gameId": 1031998, "firstBaron": false, "towerKills": [5, 7], "baronKills": [0, 1], "players": [{"firstBloodInvolve": false, "name": "FW Hanabi", "champId": 126, "firstDeath": false}, {"firstBloodInvolve": false, "name": "FW Bugi", "champId": 113, "firstDeath": false}, {"firstBloodInvolve": false, "name": "FW Rather", "champId": 3, "firstDeath": false}, {"firstBloodInvolve": false, "name": "FW Betty", "champId": 15, "firstDeath": false}, {"firstBloodInvolve": false, "name": "FW ShiauC", "champId": 497, "firstDeath": true}, {"firstBloodInvolve": false, "name": "MAD Liang", "champId": 78, "firstDeath": false}, {"firstBloodInvolve": false, "name": "MAD Kongyue", "champId": 5, "firstDeath": false}, {"firstBloodInvolve": true, "name": "MAD Uniboy", "champId": 127, "firstDeath": false}, {"firstBloodInvolve": true, "name": "MAD Breeze", "champId": 81, "firstDeath": false}, {"firstBloodInvolve": true, "name": "MAD K", "champId": 412, "firstDeath": false}], "bans": [[14, 6, 142, 223, 12], [69, 266, 84, 164, 121]], "duration": 2161, "firstBlood": 1, "patch": "9.1", "firstRiftHerald": 0, "firstInhibitor": 1, "firstDragon": 1, "teamNames": ["FW", "MAD"], "inhibitorKills": [0, 1], "dragonKills": [0, 5], "firstTower": 0, "time": 1547906678951}, {"win": 0, "gameId": 990798, "firstBaron": 0, "towerKills": [8, 4], "baronKills": [1, 0], "players": [{"firstBloodInvolve": true, "name": "MAD Liang", "champId": 14, "firstDeath": false}, {"firstBloodInvolve": true, "name": "MAD Kongyue", "champId": 121, "firstDeath": false}, {"firstBloodInvolve": false, "name": "MAD Uniboy", "champId": 3, "firstDeath": false}, {"firstBloodInvolve": false, "name": "MAD Breeze", "champId": 51, "firstDeath": false}, {"firstBloodInvolve": false, "name": "MAD K", "champId": 497, "firstDeath": false}, {"firstBloodInvolve": false, "name": "FW Hanabi", "champId": 39, "firstDeath": true}, {"firstBloodInvolve": false, "name": "FW Bugi", "champId": 79, "firstDeath": false}, {"firstBloodInvolve": false, "name": "FW Rather", "champId": 161, "firstDeath": false}, {"firstBloodInvolve": false, "name": "FW Betty", "champId": 81, "firstDeath": false}, {"firstBloodInvolve": false, "name": "FW ShiauC", "champId": 223, "firstDeath": false}], "bans": [[236, 113, 84, 8, 127], [69, 266, 6, 25, 5]], "duration": 2487, "firstBlood": 0, "patch": "9.1", "firstRiftHerald": 0, "firstInhibitor": 0, "firstDragon": 0, "teamNames": ["MAD", "FW"], "inhibitorKills": [1, 0], "dragonKills": [3, 3], "firstTower": 1, "time": 1547902181800}, {"win": 0, "gameId": 1031967, "firstBaron": 0, "towerKills": [11, 1], "baronKills": [1, 0], "players": [{"firstBloodInvolve": false, "name": "FW Hanabi", "champId": 6, "firstDeath": false}, {"firstBloodInvolve": false, "name": "FW Bugi", "champId": 163, "firstDeath": false}, {"firstBloodInvolve": false, "name": "FW Rather", "champId": 8, "firstDeath": false}, {"firstBloodInvolve": false, "name": "FW Betty", "champId": 236, "firstDeath": true}, {"firstBloodInvolve": false, "name": "FW ShiauC", "champId": 12, "firstDeath": false}, {"firstBloodInvolve": false, "name": "MAD Liang", "champId": 39, "firstDeath": false}, {"firstBloodInvolve": true, "name": "MAD Kongyue", "champId": 164, "firstDeath": false}, {"firstBloodInvolve": true, "name": "MAD Uniboy", "champId": 3, "firstDeath": false}, {"firstBloodInvolve": true, "name": "MAD Breeze", "champId": 112, "firstDeath": false}, {"firstBloodInvolve": true, "name": "MAD K", "champId": 412, "firstDeath": false}], "bans": [[223, 81, 25, 145, 14], [69, 266, 84, 5, 113]], "duration": 1723, "firstBlood": 1, "patch": "9.1", "firstRiftHerald": 0, "firstInhibitor": 0, "firstDragon": 1, "teamNames": ["FW", "MAD"], "inhibitorKills": [2, 0], "dragonKills": [3, 1], "firstTower": 0, "time": 1547897160437}, {"win": 1, "gameId": 980667, "firstBaron": false, "towerKills": [0, 11], "baronKills": [0, 1], "players": [{"firstBloodInvolve": false, "name": "AHQ Ziv", "champId": 112, "firstDeath": false}, {"firstBloodInvolve": false, "name": "AHQ Baby", "champId": 121, "firstDeath": false}, {"firstBloodInvolve": false, "name": "AHQ Wako", "champId": 3, "firstDeath": false}, {"firstBloodInvolve": true, "name": "AHQ An", "champId": 145, "firstDeath": false}, {"firstBloodInvolve": true, "name": "AHQ Kino", "champId": 89, "firstDeath": false}, {"firstBloodInvolve": false, "name": "JT Rest", "champId": 84, "firstDeath": false}, {"firstBloodInvolve": false, "name": "JT Hana", "champId": 5, "firstDeath": false}, {"firstBloodInvolve": false, "name": "JT FoFo", "champId": 14, "firstDeath": false}, {"firstBloodInvolve": false, "name": "JT Lilv", "champId": 81, "firstDeath": false}, {"firstBloodInvolve": false, "name": "JT Koala", "champId": 201, "firstDeath": true}], "bans": [[39, 236, 497, 25, 223], [266, 69, 6, 8, 12]], "duration": 1871, "firstBlood": 0, "patch": "9.1", "firstRiftHerald": 1, "firstInhibitor": 1, "firstDragon": 0, "teamNames": ["AHQ", "JT"], "inhibitorKills": [0, 2], "dragonKills": [1, 3], "firstTower": 1, "time": 1547893163214}, {"win": 0, "gameId": 1031935, "firstBaron": 0, "towerKills": [11, 2], "baronKills": [2, 0], "players": [{"firstBloodInvolve": false, "name": "JT Rest", "champId": 14, "firstDeath": false}, {"firstBloodInvolve": false, "name": "JT Hana", "champId": 79, "firstDeath": true}, {"firstBloodInvolve": false, "name": "JT FoFo", "champId": 236, "firstDeath": false}, {"firstBloodInvolve": false, "name": "JT Lilv", "champId": 112, "firstDeath": false}, {"firstBloodInvolve": false, "name": "JT Koala", "champId": 223, "firstDeath": false}, {"firstBloodInvolve": false, "name": "AHQ Ziv", "champId": 6, "firstDeath": false}, {"firstBloodInvolve": true, "name": "AHQ Baby", "champId": 121, "firstDeath": false}, {"firstBloodInvolve": true, "name": "AHQ Rainbow", "champId": 3, "firstDeath": false}, {"firstBloodInvolve": false, "name": "AHQ An", "champId": 145, "firstDeath": false}, {"firstBloodInvolve": false, "name": "AHQ Kino", "champId": 412, "firstDeath": false}], "bans": [[5, 497, 127, 16, 12], [69, 39, 266, 8, 142]], "duration": 2602, "firstBlood": 1, "patch": "9.1", "firstRiftHerald": 1, "firstInhibitor": 0, "firstDragon": 0, "teamNames": ["JT", "AHQ"], "inhibitorKills": [2, 0], "dragonKills": [4, 2], "firstTower": 0, "time": 1547886818813}, {"win": 0, "gameId": 1031795, "firstBaron": 0, "towerKills": [7, 0], "baronKills": [1, 0], "players": [{"firstBloodInvolve": false, "name": "FW Hanabi", "champId": 6, "firstDeath": false}, {"firstBloodInvolve": false, "name": "FW Bugi", "champId": 79, "firstDeath": false}, {"firstBloodInvolve": false, "name": "FW Rather", "champId": 8, "firstDeath": true}, {"firstBloodInvolve": false, "name": "FW Betty", "champId": 81, "firstDeath": false}, {"firstBloodInvolve": false, "name": "FW ShiauC", "champId": 223, "firstDeath": false}, {"firstBloodInvolve": false, "name": "HKA 3z", "champId": 112, "firstDeath": false}, {"firstBloodInvolve": true, "name": "HKA Gemini", "champId": 164, "firstDeath": false}, {"firstBloodInvolve": true, "name": "HKA Error", "champId": 39, "firstDeath": false}, {"firstBloodInvolve": false, "name": "HKA Unified", "champId": 15, "firstDeath": false}, {"firstBloodInvolve": false, "name": "HKA Kaiwing", "champId": 113, "firstDeath": false}], "bans": [[126, 3, 127, 201, 497], [69, 266, 84, 7, 5]], "duration": 1632, "firstBlood": 1, "patch": "9.1", "firstRiftHerald": 1, "firstInhibitor": 0, "firstDragon": 0, "teamNames": ["FW", "HKA"], "inhibitorKills": [1, 0], "dragonKills": [2, 0], "firstTower": 0, "time": 1547821067115}, {"win": 0, "gameId": 990635, "firstBaron": 0, "towerKills": [10, 5], "baronKills": [2, 0], "players": [{"firstBloodInvolve": false, "name": "HKA 3z", "champId": 126, "firstDeath": true}, {"firstBloodInvolve": false, "name": "HKA Gemini", "champId": 121, "firstDeath": false}, {"firstBloodInvolve": false, "name": "HKA Error", "champId": 3, "firstDeath": false}, {"firstBloodInvolve": false, "name": "HKA Unified", "champId": 498, "firstDeath": false}, {"firstBloodInvolve": false, "name": "HKA Kaiwing", "champId": 497, "firstDeath": false}, {"firstBloodInvolve": false, "name": "FW Hanabi", "champId": 6, "firstDeath": false}, {"firstBloodInvolve": true, "name": "FW Bugi", "champId": 113, "firstDeath": false}, {"firstBloodInvolve": false, "name": "FW Rather", "champId": 236, "firstDeath": false}, {"firstBloodInvolve": false, "name": "FW Betty", "champId": 145, "firstDeath": false}, {"firstBloodInvolve": false, "name": "FW ShiauC", "champId": 412, "firstDeath": false}], "bans": [[14, 5, 12, 201, 39], [69, 266, 164, 81, 110]], "duration": 1930, "firstBlood": 1, "patch": "9.1", "firstRiftHerald": 1, "firstInhibitor": 0, "firstDragon": 0, "teamNames": ["HKA", "FW"], "inhibitorKills": [1, 0], "dragonKills": [2, 2], "firstTower": 1, "time": 1547817231635}, {"win": 1, "gameId": 1031777, "firstBaron": false, "towerKills": [2, 9], "baronKills": [0, 1], "players": [{"firstBloodInvolve": false, "name": "HKA 3z", "champId": 6, "firstDeath": true}, {"firstBloodInvolve": false, "name": "HKA Gemini", "champId": 64, "firstDeath": false}, {"firstBloodInvolve": false, "name": "HKA M1ssion", "champId": 134, "firstDeath": false}, {"firstBloodInvolve": false, "name": "HKA Unified", "champId": 110, "firstDeath": false}, {"firstBloodInvolve": false, "name": "HKA Kaiwing", "champId": 223, "firstDeath": false}, {"firstBloodInvolve": true, "name": "FW Hanabi", "champId": 84, "firstDeath": false}, {"firstBloodInvolve": true, "name": "FW Bugi", "champId": 5, "firstDeath": false}, {"firstBloodInvolve": true, "name": "FW Rather", "champId": 127, "firstDeath": false}, {"firstBloodInvolve": false, "name": "FW Betty", "champId": 81, "firstDeath": false}, {"firstBloodInvolve": false, "name": "FW ShiauC", "champId": 201, "firstDeath": false}], "bans": [[164, 14, 3, 12, 412], [69, 266, 142, 25, 236]], "duration": 1623, "firstBlood": 1, "patch": "9.1", "firstRiftHerald": 1, "firstInhibitor": 1, "firstDragon": 0, "teamNames": ["HKA", "FW"], "inhibitorKills": [0, 2], "dragonKills": [1, 3], "firstTower": 0, "time": 1547812472889}, {"win": 1, "gameId": 1031772, "firstBaron": false, "towerKills": [1, 9], "baronKills": [0, 0], "players": [{"firstBloodInvolve": false, "name": "ALF Leaky", "champId": 6, "firstDeath": false}, {"firstBloodInvolve": false, "name": "ALF Gengar", "champId": 113, "firstDeath": false}, {"firstBloodInvolve": false, "name": "ALF Caipi", "champId": 142, "firstDeath": false}, {"firstBloodInvolve": false, "name": "ALF DDC", "champId": 81, "firstDeath": false}, {"firstBloodInvolve": false, "name": "ALF SkuLL", "champId": 223, "firstDeath": false}, {"firstBloodInvolve": false, "name": "DG 2188", "champId": 14, "firstDeath": true}, {"firstBloodInvolve": false, "name": "DG JGY", "champId": 64, "firstDeath": false}, {"firstBloodInvolve": false, "name": "DG Xiaobo", "champId": 127, "firstDeath": false}, {"firstBloodInvolve": false, "name": "DG YuLun", "champId": 145, "firstDeath": false}, {"firstBloodInvolve": false, "name": "DG pasa", "champId": 12, "firstDeath": false}], "bans": [[236, 76, 69, 497, 201], [266, 39, 3, 5, 164]], "duration": 1265, "firstBlood": 1, "patch": "9.1", "firstRiftHerald": 0, "firstInhibitor": 1, "firstDragon": 1, "teamNames": ["ALF", "DG"], "inhibitorKills": [0, 1], "dragonKills": [0, 2], "firstTower": 1, "time": 1547809750119}, {"win": 0, "gameId": 980537, "firstBaron": 0, "towerKills": [8, 10], "baronKills": [1, 1], "players": [{"firstBloodInvolve": false, "name": "ALF Leaky", "champId": 8, "firstDeath": false}, {"firstBloodInvolve": true, "name": "ALF Gengar", "champId": 113, "firstDeath": false}, {"firstBloodInvolve": true, "name": "ALF Caipi", "champId": 39, "firstDeath": false}, {"firstBloodInvolve": true, "name": "ALF DDC", "champId": 81, "firstDeath": false}, {"firstBloodInvolve": false, "name": "ALF SkuLL", "champId": 223, "firstDeath": false}, {"firstBloodInvolve": false, "name": "DG 2188", "champId": 6, "firstDeath": false}, {"firstBloodInvolve": false, "name": "DG JGY", "champId": 79, "firstDeath": true}, {"firstBloodInvolve": false, "name": "DG Xiaobo", "champId": 7, "firstDeath": false}, {"firstBloodInvolve": false, "name": "DG YuLun", "champId": 145, "firstDeath": false}, {"firstBloodInvolve": false, "name": "DG pasa", "champId": 497, "firstDeath": false}], "bans": [[236, 69, 76, 498, 64], [266, 3, 164, 12, 25]], "duration": 2605, "firstBlood": 0, "patch": "9.1", "firstRiftHerald": 1, "firstInhibitor": 1, "firstDragon": 0, "teamNames": ["ALF", "DG"], "inhibitorKills": [1, 2], "dragonKills": [2, 3], "firstTower": 0, "time": 1547804859804}, {"win": 1, "gameId": 1031732, "firstBaron": false, "towerKills": [3, 9], "baronKills": [0, 1], "players": [{"firstBloodInvolve": false, "name": "ALF Leaky", "champId": 6, "firstDeath": false}, {"firstBloodInvolve": false, "name": "ALF WSY", "champId": 59, "firstDeath": false}, {"firstBloodInvolve": false, "name": "ALF Caipi", "champId": 142, "firstDeath": false}, {"firstBloodInvolve": false, "name": "ALF DDC", "champId": 22, "firstDeath": false}, {"firstBloodInvolve": false, "name": "ALF SkuLL", "champId": 223, "firstDeath": true}, {"firstBloodInvolve": false, "name": "DG 2188", "champId": 78, "firstDeath": false}, {"firstBloodInvolve": true, "name": "DG JGY", "champId": 76, "firstDeath": false}, {"firstBloodInvolve": false, "name": "DG Xiaobo", "champId": 127, "firstDeath": false}, {"firstBloodInvolve": true, "name": "DG YuLun", "champId": 236, "firstDeath": false}, {"firstBloodInvolve": true, "name": "DG pasa", "champId": 201, "firstDeath": false}], "bans": [[84, 69, 39, 14, 64], [266, 3, 164, 110, 81]], "duration": 1400, "firstBlood": 1, "patch": "9.1", "firstRiftHerald": 1, "firstInhibitor": 1, "firstDragon": 1, "teamNames": ["ALF", "DG"], "inhibitorKills": [0, 1], "dragonKills": [1, 2], "firstTower": 1, "time": 1547801342487}, {"win": 0, "gameId": 990401, "firstBaron": 0, "towerKills": [9, 3], "baronKills": [1, 0], "players": [{"firstBloodInvolve": false, "name": "MAD Liang", "champId": 14, "firstDeath": false}, {"firstBloodInvolve": false, "name": "MAD Kongyue", "champId": 121, "firstDeath": false}, {"firstBloodInvolve": false, "name": "MAD Uniboy", "champId": 3, "firstDeath": false}, {"firstBloodInvolve": false, "name": "MAD Breeze", "champId": 51, "firstDeath": false}, {"firstBloodInvolve": false, "name": "MAD K", "champId": 25, "firstDeath": true}, {"firstBloodInvolve": false, "name": "AHQ Ziv", "champId": 8, "firstDeath": false}, {"firstBloodInvolve": false, "name": "AHQ Baby", "champId": 79, "firstDeath": false}, {"firstBloodInvolve": false, "name": "AHQ Rainbow", "champId": 6, "firstDeath": false}, {"firstBloodInvolve": true, "name": "AHQ An", "champId": 145, "firstDeath": false}, {"firstBloodInvolve": false, "name": "AHQ Kino", "champId": 16, "firstDeath": false}], "bans": [[84, 236, 164, 142, 127], [69, 266, 39, 5, 56]], "duration": 1735, "firstBlood": 1, "patch": "9.1", "firstRiftHerald": 0, "firstInhibitor": 0, "firstDragon": 1, "teamNames": ["MAD", "AHQ"], "inhibitorKills": [2, 0], "dragonKills": [1, 3], "firstTower": 1, "time": 1547730178135}, {"win": 1, "gameId": 1031533, "firstBaron": 0, "towerKills": [4, 7], "baronKills": [1, 1], "players": [{"firstBloodInvolve": false, "name": "AHQ Ziv", "champId": 14, "firstDeath": false}, {"firstBloodInvolve": false, "name": "AHQ Baby", "champId": 266, "firstDeath": true}, {"firstBloodInvolve": false, "name": "AHQ Rainbow", "champId": 127, "firstDeath": false}, {"firstBloodInvolve": false, "name": "AHQ An", "champId": 145, "firstDeath": false}, {"firstBloodInvolve": false, "name": "AHQ Kino", "champId": 89, "firstDeath": false}, {"firstBloodInvolve": false, "name": "MAD Liang", "champId": 6, "firstDeath": false}, {"firstBloodInvolve": true, "name": "MAD Kongyue", "champId": 79, "firstDeath": false}, {"firstBloodInvolve": true, "name": "MAD Uniboy", "champId": 3, "firstDeath": false}, {"firstBloodInvolve": true, "name": "MAD Breeze", "champId": 81, "firstDeath": false}, {"firstBloodInvolve": true, "name": "MAD K", "champId": 497, "firstDeath": false}], "bans": [[39, 164, 142, 498, 5], [69, 84, 236, 412, 12]], "duration": 2287, "firstBlood": 1, "patch": "9.1", "firstRiftHerald": 1, "firstInhibitor": 1, "firstDragon": 0, "teamNames": ["AHQ", "MAD"], "inhibitorKills": [0, 1], "dragonKills": [2, 3], "firstTower": 0, "time": 1547724906809}, {"win": 0, "gameId": 1031514, "firstBaron": 0, "towerKills": [9, 1], "baronKills": [1, 0], "players": [{"firstBloodInvolve": true, "name": "JT Rest", "champId": 6, "firstDeath": false}, {"firstBloodInvolve": true, "name": "JT Breaker", "champId": 121, "firstDeath": false}, {"firstBloodInvolve": true, "name": "JT FoFo", "champId": 7, "firstDeath": false}, {"firstBloodInvolve": false, "name": "JT Lilv", "champId": 145, "firstDeath": false}, {"firstBloodInvolve": false, "name": "JT Koala", "champId": 12, "firstDeath": false}, {"firstBloodInvolve": false, "name": "GRX PK", "champId": 8, "firstDeath": true}, {"firstBloodInvolve": false, "name": "GRX Raise", "champId": 72, "firstDeath": false}, {"firstBloodInvolve": false, "name": "GRX Wuji", "champId": 39, "firstDeath": false}, {"firstBloodInvolve": false, "name": "GRX Atlen", "champId": 15, "firstDeath": false}, {"firstBloodInvolve": false, "name": "GRX Eason", "champId": 497, "firstDeath": false}], "bans": [[127, 3, 14, 113, 154], [266, 69, 236, 157, 84]], "duration": 2256, "firstBlood": 0, "patch": "9.1", "firstRiftHerald": 0, "firstInhibitor": 0, "firstDragon": 0, "teamNames": ["JT", "GRX"], "inhibitorKills": [2, 0], "dragonKills": [5, 1], "firstTower": 1, "time": 1547720557658}, {"win": 1, "gameId": 1010119, "firstBaron": false, "towerKills": [4, 8], "baronKills": [0, 1], "players": [{"firstBloodInvolve": true, "name": "GRX PK", "champId": 6, "firstDeath": false}, {"firstBloodInvolve": true, "name": "GRX Raise", "champId": 79, "firstDeath": false}, {"firstBloodInvolve": true, "name": "GRX Wuji", "champId": 127, "firstDeath": false}, {"firstBloodInvolve": false, "name": "GRX Atlen", "champId": 498, "firstDeath": false}, {"firstBloodInvolve": false, "name": "GRX Eason", "champId": 12, "firstDeath": false}, {"firstBloodInvolve": false, "name": "JT Rest", "champId": 14, "firstDeath": false}, {"firstBloodInvolve": false, "name": "JT Hana", "champId": 154, "firstDeath": true}, {"firstBloodInvolve": false, "name": "JT FoFo", "champId": 8, "firstDeath": false}, {"firstBloodInvolve": false, "name": "JT Lilv", "champId": 81, "firstDeath": false}, {"firstBloodInvolve": false, "name": "JT Koala", "champId": 497, "firstDeath": false}], "bans": [[39, 112, 236, 142, 3], [69, 266, 121, 145, 15]], "duration": 2382, "firstBlood": 0, "patch": "9.1", "firstRiftHerald": 0, "firstInhibitor": 1, "firstDragon": 0, "teamNames": ["GRX", "JT"], "inhibitorKills": [0, 1], "dragonKills": [4, 1], "firstTower": 0, "time": 1547715996181}]