{"ALF": {"firstTowerPosition": {"TOP_LANE": 2, "MID_LANE": 0, "BOT_LANE": 3}, "blueDragonKills": 8, "firstBloodPositions": [], "blueBaronKills": 3, "redFirstDeathPlayers": {"ALF WSY": 0, "ALF SkuLL": 2, "ALF Caipi": 0, "ALF Xiaoemo": 1, "ALF Kiwi": 0, "ALF Leaky": 1, "ALF Gengar": 0, "ALF DDC": 0}, "redFirstBloods": 3, "firstBarons": 3, "redMatchesPlayed": 7, "redTowerKills": 27, "redFirstBloodAssistPlayers": {"ALF WSY": 1, "ALF SkuLL": 1, "ALF Caipi": 1, "ALF Xiaoemo": 0, "ALF Kiwi": 0, "ALF Leaky": 1, "ALF Gengar": 0, "ALF DDC": 0}, "firstEnemyTowerPosition": {"TOP_LANE": 1, "MID_LANE": 3, "BOT_LANE": 4}, "playersMatchesPlayed": {"ALF WSY": 10, "ALF SkuLL": 13, "ALF Caipi": 13, "ALF Xiaoemo": 10, "ALF Kiwi": 1, "ALF Leaky": 13, "ALF Gengar": 2, "ALF DDC": 3}, "firstDragons": 4, "redFirstTowers": 3, "dragonKills": 25, "bluePlayersMatchesPlayed": {"ALF WSY": 0, "ALF SkuLL": 0, "ALF Caipi": 0, "ALF Xiaoemo": 0, "ALF Kiwi": 0, "ALF Leaky": 0, "ALF Gengar": 0, "ALF DDC": 0}, "firstTowers": 5, "blueFirstInhibs": 2, "firstDeathPositions": [], "redFirstBloodPlayers": {"ALF WSY": 2, "ALF SkuLL": 0, "ALF Caipi": 0, "ALF Xiaoemo": 0, "ALF Kiwi": 0, "ALF Leaky": 1, "ALF Gengar": 0, "ALF DDC": 0}, "redWins": 2, "redDragonKills": 17, "redBaronKills": 3, "redInhibitorKills": 4, "blueFirstDragons": 3, "matchesPlayed": 13, "blueWins": 2, "firstInhibs": 4, "blueFirstBarons": 3, "firstRedTowerPosition": {"TOP_LANE": 2, "MID_LANE": 0, "BOT_LANE": 1}, "totalWins": 4, "blueFirstBloods": 4, "blueTowerKills": 31, "redFirstHeralds": 3, "blueInhibitorKills": 3, "firstDeathPlayers": {"ALF WSY": 0, "ALF SkuLL": 3, "ALF Caipi": 0, "ALF Xiaoemo": 1, "ALF Kiwi": 0, "ALF Leaky": 1, "ALF Gengar": 0, "ALF DDC": 0}, "firstBloodAssistPlayers": {"ALF WSY": 2, "ALF SkuLL": 2, "ALF Caipi": 2, "ALF Xiaoemo": 2, "ALF Kiwi": 1, "ALF Leaky": 1, "ALF Gengar": 1, "ALF DDC": 0}, "blueFirstHeralds": 3, "firstBlueTowerPosition": {"TOP_LANE": 0, "MID_LANE": 0, "BOT_LANE": 2}, "firstBloodPlayers": {"ALF WSY": 3, "ALF SkuLL": 1, "ALF Caipi": 1, "ALF Xiaoemo": 0, "ALF Kiwi": 0, "ALF Leaky": 1, "ALF Gengar": 0, "ALF DDC": 1}, "firstHeralds": 6, "blueFirstBloodPlayers": {"ALF WSY": 1, "ALF SkuLL": 1, "ALF Caipi": 1, "ALF Xiaoemo": 0, "ALF Kiwi": 0, "ALF Leaky": 0, "ALF Gengar": 0, "ALF DDC": 1}, "blueFirstDeathPlayers": {"ALF WSY": 0, "ALF SkuLL": 1, "ALF Caipi": 0, "ALF Xiaoemo": 0, "ALF Kiwi": 0, "ALF Leaky": 0, "ALF Gengar": 0, "ALF DDC": 0}, "inhibitorKills": 7, "blueFirstTowers": 2, "redFirstDragons": 1, "redFirstBarons": 0, "firstRedEnemyTowerPosition": {"TOP_LANE": 1, "MID_LANE": 1, "BOT_LANE": 2}, "redPlayersMatchesPlayed": {"ALF WSY": 0, "ALF SkuLL": 0, "ALF Caipi": 0, "ALF Xiaoemo": 0, "ALF Kiwi": 0, "ALF Leaky": 0, "ALF Gengar": 0, "ALF DDC": 0}, "baronKills": 6, "blueFirstBloodAssistPlayers": {"ALF WSY": 1, "ALF SkuLL": 1, "ALF Caipi": 1, "ALF Xiaoemo": 2, "ALF Kiwi": 1, "ALF Leaky": 0, "ALF Gengar": 1, "ALF DDC": 0}, "firstBloods": 7, "blueMatchesPlayed": 6, "redFirstInhibs": 2, "towerKills": 58, "firstBlueEnemyTowerPosition": {"TOP_LANE": 0, "MID_LANE": 2, "BOT_LANE": 2}}, "GRX": {"firstTowerPosition": {"TOP_LANE": 3, "MID_LANE": 0, "BOT_LANE": 7}, "blueDragonKills": 23, "firstBloodPositions": [], "blueBaronKills": 6, "redFirstDeathPlayers": {"GRX Wuji": 1, "GRX PK": 2, "GRX Eason": 0, "GRX Raise": 1, "GRX Atlen": 0, "GRX Bruce": 2, "GRX Yoon": 2}, "redFirstBloods": 1, "firstBarons": 4, "redMatchesPlayed": 9, "redTowerKills": 35, "redFirstBloodAssistPlayers": {"GRX Wuji": 0, "GRX PK": 0, "GRX Eason": 0, "GRX Raise": 0, "GRX Atlen": 0, "GRX Bruce": 0, "GRX Yoon": 1}, "firstEnemyTowerPosition": {"TOP_LANE": 3, "MID_LANE": 2, "BOT_LANE": 2}, "playersMatchesPlayed": {"GRX Wuji": 17, "GRX PK": 17, "GRX Eason": 2, "GRX Raise": 17, "GRX Atlen": 2, "GRX Bruce": 15, "GRX Yoon": 15}, "firstDragons": 9, "redFirstTowers": 4, "dragonKills": 37, "bluePlayersMatchesPlayed": {"GRX Wuji": 0, "GRX PK": 0, "GRX Eason": 0, "GRX Raise": 0, "GRX Atlen": 0, "GRX Bruce": 0, "GRX Yoon": 0}, "firstTowers": 10, "blueFirstInhibs": 4, "firstDeathPositions": [], "redFirstBloodPlayers": {"GRX Wuji": 0, "GRX PK": 0, "GRX Eason": 0, "GRX Raise": 0, "GRX Atlen": 0, "GRX Bruce": 1, "GRX Yoon": 0}, "redWins": 3, "redDragonKills": 14, "redBaronKills": 4, "redInhibitorKills": 5, "blueFirstDragons": 5, "matchesPlayed": 17, "blueWins": 4, "firstInhibs": 7, "blueFirstBarons": 4, "firstRedTowerPosition": {"TOP_LANE": 1, "MID_LANE": 0, "BOT_LANE": 3}, "totalWins": 7, "blueFirstBloods": 7, "blueTowerKills": 56, "redFirstHeralds": 1, "blueInhibitorKills": 10, "firstDeathPlayers": {"GRX Wuji": 2, "GRX PK": 2, "GRX Eason": 0, "GRX Raise": 1, "GRX Atlen": 0, "GRX Bruce": 2, "GRX Yoon": 2}, "firstBloodAssistPlayers": {"GRX Wuji": 2, "GRX PK": 2, "GRX Eason": 0, "GRX Raise": 3, "GRX Atlen": 0, "GRX Bruce": 2, "GRX Yoon": 7}, "blueFirstHeralds": 8, "firstBlueTowerPosition": {"TOP_LANE": 2, "MID_LANE": 0, "BOT_LANE": 4}, "firstBloodPlayers": {"GRX Wuji": 3, "GRX PK": 0, "GRX Eason": 0, "GRX Raise": 1, "GRX Atlen": 0, "GRX Bruce": 4, "GRX Yoon": 0}, "firstHeralds": 9, "blueFirstBloodPlayers": {"GRX Wuji": 3, "GRX PK": 0, "GRX Eason": 0, "GRX Raise": 1, "GRX Atlen": 0, "GRX Bruce": 3, "GRX Yoon": 0}, "blueFirstDeathPlayers": {"GRX Wuji": 1, "GRX PK": 0, "GRX Eason": 0, "GRX Raise": 0, "GRX Atlen": 0, "GRX Bruce": 0, "GRX Yoon": 0}, "inhibitorKills": 15, "blueFirstTowers": 6, "redFirstDragons": 4, "redFirstBarons": 0, "firstRedEnemyTowerPosition": {"TOP_LANE": 2, "MID_LANE": 1, "BOT_LANE": 2}, "redPlayersMatchesPlayed": {"GRX Wuji": 0, "GRX PK": 0, "GRX Eason": 0, "GRX Raise": 0, "GRX Atlen": 0, "GRX Bruce": 0, "GRX Yoon": 0}, "baronKills": 10, "blueFirstBloodAssistPlayers": {"GRX Wuji": 2, "GRX PK": 2, "GRX Eason": 0, "GRX Raise": 3, "GRX Atlen": 0, "GRX Bruce": 2, "GRX Yoon": 6}, "firstBloods": 8, "blueMatchesPlayed": 8, "redFirstInhibs": 3, "towerKills": 91, "firstBlueEnemyTowerPosition": {"TOP_LANE": 1, "MID_LANE": 1, "BOT_LANE": 0}}, "HKA": {"firstTowerPosition": {"TOP_LANE": 0, "MID_LANE": 3, "BOT_LANE": 6}, "blueDragonKills": 20, "firstBloodPositions": [], "blueBaronKills": 8, "redFirstDeathPlayers": {"HKA Unified": 1, "HKA Kaiwing": 0, "HKA MnM": 0, "HKA Crash": 0, "HKA 3z": 0, "HKA Gemini": 1, "HKA M1ssion": 0, "HKA Error": 0}, "redFirstBloods": 5, "firstBarons": 5, "redMatchesPlayed": 7, "redTowerKills": 41, "redFirstBloodAssistPlayers": {"HKA Unified": 1, "HKA Kaiwing": 3, "HKA MnM": 0, "HKA Crash": 2, "HKA 3z": 0, "HKA Gemini": 2, "HKA M1ssion": 0, "HKA Error": 1}, "firstEnemyTowerPosition": {"TOP_LANE": 1, "MID_LANE": 0, "BOT_LANE": 4}, "playersMatchesPlayed": {"HKA Unified": 9, "HKA Kaiwing": 14, "HKA MnM": 5, "HKA Crash": 5, "HKA 3z": 14, "HKA Gemini": 9, "HKA M1ssion": 11, "HKA Error": 3}, "firstDragons": 11, "redFirstTowers": 4, "dragonKills": 42, "bluePlayersMatchesPlayed": {"HKA Unified": 0, "HKA Kaiwing": 0, "HKA MnM": 0, "HKA Crash": 0, "HKA 3z": 0, "HKA Gemini": 0, "HKA M1ssion": 0, "HKA Error": 0}, "firstTowers": 9, "blueFirstInhibs": 5, "firstDeathPositions": [], "redFirstBloodPlayers": {"HKA Unified": 0, "HKA Kaiwing": 0, "HKA MnM": 1, "HKA Crash": 0, "HKA 3z": 0, "HKA Gemini": 1, "HKA M1ssion": 3, "HKA Error": 0}, "redWins": 3, "redDragonKills": 22, "redBaronKills": 5, "redInhibitorKills": 8, "blueFirstDragons": 5, "matchesPlayed": 14, "blueWins": 5, "firstInhibs": 8, "blueFirstBarons": 5, "firstRedTowerPosition": {"TOP_LANE": 0, "MID_LANE": 3, "BOT_LANE": 1}, "totalWins": 8, "blueFirstBloods": 4, "blueTowerKills": 53, "redFirstHeralds": 2, "blueInhibitorKills": 8, "firstDeathPlayers": {"HKA Unified": 1, "HKA Kaiwing": 0, "HKA MnM": 0, "HKA Crash": 0, "HKA 3z": 2, "HKA Gemini": 2, "HKA M1ssion": 0, "HKA Error": 0}, "firstBloodAssistPlayers": {"HKA Unified": 1, "HKA Kaiwing": 5, "HKA MnM": 1, "HKA Crash": 2, "HKA 3z": 1, "HKA Gemini": 3, "HKA M1ssion": 1, "HKA Error": 1}, "blueFirstHeralds": 2, "firstBlueTowerPosition": {"TOP_LANE": 0, "MID_LANE": 0, "BOT_LANE": 5}, "firstBloodPlayers": {"HKA Unified": 0, "HKA Kaiwing": 0, "HKA MnM": 2, "HKA Crash": 1, "HKA 3z": 1, "HKA Gemini": 2, "HKA M1ssion": 3, "HKA Error": 0}, "firstHeralds": 4, "blueFirstBloodPlayers": {"HKA Unified": 0, "HKA Kaiwing": 0, "HKA MnM": 1, "HKA Crash": 1, "HKA 3z": 1, "HKA Gemini": 1, "HKA M1ssion": 0, "HKA Error": 0}, "blueFirstDeathPlayers": {"HKA Unified": 0, "HKA Kaiwing": 0, "HKA MnM": 0, "HKA Crash": 0, "HKA 3z": 2, "HKA Gemini": 1, "HKA M1ssion": 0, "HKA Error": 0}, "inhibitorKills": 16, "blueFirstTowers": 5, "redFirstDragons": 6, "redFirstBarons": 0, "firstRedEnemyTowerPosition": {"TOP_LANE": 0, "MID_LANE": 0, "BOT_LANE": 3}, "redPlayersMatchesPlayed": {"HKA Unified": 0, "HKA Kaiwing": 0, "HKA MnM": 0, "HKA Crash": 0, "HKA 3z": 0, "HKA Gemini": 0, "HKA M1ssion": 0, "HKA Error": 0}, "baronKills": 13, "blueFirstBloodAssistPlayers": {"HKA Unified": 0, "HKA Kaiwing": 2, "HKA MnM": 1, "HKA Crash": 0, "HKA 3z": 1, "HKA Gemini": 1, "HKA M1ssion": 1, "HKA Error": 0}, "firstBloods": 9, "blueMatchesPlayed": 7, "redFirstInhibs": 3, "towerKills": 94, "firstBlueEnemyTowerPosition": {"TOP_LANE": 1, "MID_LANE": 0, "BOT_LANE": 1}}, "MAD": {"firstTowerPosition": {"TOP_LANE": 1, "MID_LANE": 0, "BOT_LANE": 1}, "blueDragonKills": 13, "firstBloodPositions": [], "blueBaronKills": 7, "redFirstDeathPlayers": {"MAD K": 0, "MAD Uniboy": 0, "MAD Kongyue": 1, "MAD Liang": 0, "MAD Breeze": 2, "MAD Rock": 0}, "redFirstBloods": 3, "firstBarons": 5, "redMatchesPlayed": 6, "redTowerKills": 32, "redFirstBloodAssistPlayers": {"MAD K": 3, "MAD Uniboy": 2, "MAD Kongyue": 1, "MAD Liang": 0, "MAD Breeze": 2, "MAD Rock": 0}, "firstEnemyTowerPosition": {"TOP_LANE": 3, "MID_LANE": 1, "BOT_LANE": 8}, "playersMatchesPlayed": {"MAD K": 14, "MAD Uniboy": 14, "MAD Kongyue": 14, "MAD Liang": 8, "MAD Breeze": 14, "MAD Rock": 6}, "firstDragons": 7, "redFirstTowers": 0, "dragonKills": 25, "bluePlayersMatchesPlayed": {"MAD K": 0, "MAD Uniboy": 0, "MAD Kongyue": 0, "MAD Liang": 0, "MAD Breeze": 0, "MAD Rock": 0}, "firstTowers": 2, "blueFirstInhibs": 5, "firstDeathPositions": [], "redFirstBloodPlayers": {"MAD K": 0, "MAD Uniboy": 1, "MAD Kongyue": 1, "MAD Liang": 0, "MAD Breeze": 1, "MAD Rock": 0}, "redWins": 4, "redDragonKills": 12, "redBaronKills": 5, "redInhibitorKills": 4, "blueFirstDragons": 5, "matchesPlayed": 14, "blueWins": 5, "firstInhibs": 9, "blueFirstBarons": 5, "firstRedTowerPosition": {"TOP_LANE": 0, "MID_LANE": 0, "BOT_LANE": 0}, "totalWins": 9, "blueFirstBloods": 3, "blueTowerKills": 50, "redFirstHeralds": 2, "blueInhibitorKills": 9, "firstDeathPlayers": {"MAD K": 2, "MAD Uniboy": 0, "MAD Kongyue": 1, "MAD Liang": 0, "MAD Breeze": 3, "MAD Rock": 2}, "firstBloodAssistPlayers": {"MAD K": 5, "MAD Uniboy": 2, "MAD Kongyue": 2, "MAD Liang": 1, "MAD Breeze": 3, "MAD Rock": 0}, "blueFirstHeralds": 6, "firstBlueTowerPosition": {"TOP_LANE": 1, "MID_LANE": 0, "BOT_LANE": 1}, "firstBloodPlayers": {"MAD K": 0, "MAD Uniboy": 1, "MAD Kongyue": 3, "MAD Liang": 0, "MAD Breeze": 2, "MAD Rock": 0}, "firstHeralds": 8, "blueFirstBloodPlayers": {"MAD K": 0, "MAD Uniboy": 0, "MAD Kongyue": 2, "MAD Liang": 0, "MAD Breeze": 1, "MAD Rock": 0}, "blueFirstDeathPlayers": {"MAD K": 2, "MAD Uniboy": 0, "MAD Kongyue": 0, "MAD Liang": 0, "MAD Breeze": 1, "MAD Rock": 2}, "inhibitorKills": 13, "blueFirstTowers": 2, "redFirstDragons": 2, "redFirstBarons": 0, "firstRedEnemyTowerPosition": {"TOP_LANE": 2, "MID_LANE": 0, "BOT_LANE": 4}, "redPlayersMatchesPlayed": {"MAD K": 0, "MAD Uniboy": 0, "MAD Kongyue": 0, "MAD Liang": 0, "MAD Breeze": 0, "MAD Rock": 0}, "baronKills": 12, "blueFirstBloodAssistPlayers": {"MAD K": 2, "MAD Uniboy": 0, "MAD Kongyue": 1, "MAD Liang": 1, "MAD Breeze": 1, "MAD Rock": 0}, "firstBloods": 6, "blueMatchesPlayed": 8, "redFirstInhibs": 4, "towerKills": 82, "firstBlueEnemyTowerPosition": {"TOP_LANE": 1, "MID_LANE": 1, "BOT_LANE": 4}}, "JT": {"firstTowerPosition": {"TOP_LANE": 2, "MID_LANE": 1, "BOT_LANE": 3}, "blueDragonKills": 14, "firstBloodPositions": [], "blueBaronKills": 9, "redFirstDeathPlayers": {"JT Lilv": 0, "JT Breaker": 0, "JT FoFo": 1, "JT Koala": 1, "JT Hana": 1, "JT Rest": 1}, "redFirstBloods": 2, "firstBarons": 5, "redMatchesPlayed": 6, "redTowerKills": 42, "redFirstBloodAssistPlayers": {"JT Lilv": 0, "JT Breaker": 0, "JT FoFo": 0, "JT Koala": 0, "JT Hana": 1, "JT Rest": 1}, "firstEnemyTowerPosition": {"TOP_LANE": 3, "MID_LANE": 0, "BOT_LANE": 3}, "playersMatchesPlayed": {"JT Lilv": 12, "JT Breaker": 2, "JT FoFo": 12, "JT Koala": 12, "JT Hana": 10, "JT Rest": 12}, "firstDragons": 5, "redFirstTowers": 3, "dragonKills": 25, "bluePlayersMatchesPlayed": {"JT Lilv": 0, "JT Breaker": 0, "JT FoFo": 0, "JT Koala": 0, "JT Hana": 0, "JT Rest": 0}, "firstTowers": 6, "blueFirstInhibs": 4, "firstDeathPositions": [], "redFirstBloodPlayers": {"JT Lilv": 1, "JT Breaker": 0, "JT FoFo": 1, "JT Koala": 0, "JT Hana": 0, "JT Rest": 0}, "redWins": 4, "redDragonKills": 11, "redBaronKills": 3, "redInhibitorKills": 7, "blueFirstDragons": 3, "matchesPlayed": 12, "blueWins": 5, "firstInhibs": 8, "blueFirstBarons": 5, "firstRedTowerPosition": {"TOP_LANE": 1, "MID_LANE": 0, "BOT_LANE": 2}, "totalWins": 9, "blueFirstBloods": 3, "blueTowerKills": 53, "redFirstHeralds": 4, "blueInhibitorKills": 10, "firstDeathPlayers": {"JT Lilv": 0, "JT Breaker": 0, "JT FoFo": 2, "JT Koala": 2, "JT Hana": 2, "JT Rest": 1}, "firstBloodAssistPlayers": {"JT Lilv": 1, "JT Breaker": 1, "JT FoFo": 1, "JT Koala": 2, "JT Hana": 2, "JT Rest": 2}, "blueFirstHeralds": 4, "firstBlueTowerPosition": {"TOP_LANE": 1, "MID_LANE": 1, "BOT_LANE": 1}, "firstBloodPlayers": {"JT Lilv": 1, "JT Breaker": 1, "JT FoFo": 3, "JT Koala": 0, "JT Hana": 0, "JT Rest": 0}, "firstHeralds": 8, "blueFirstBloodPlayers": {"JT Lilv": 0, "JT Breaker": 1, "JT FoFo": 2, "JT Koala": 0, "JT Hana": 0, "JT Rest": 0}, "blueFirstDeathPlayers": {"JT Lilv": 0, "JT Breaker": 0, "JT FoFo": 1, "JT Koala": 1, "JT Hana": 1, "JT Rest": 0}, "inhibitorKills": 17, "blueFirstTowers": 3, "redFirstDragons": 2, "redFirstBarons": 0, "firstRedEnemyTowerPosition": {"TOP_LANE": 1, "MID_LANE": 0, "BOT_LANE": 2}, "redPlayersMatchesPlayed": {"JT Lilv": 0, "JT Breaker": 0, "JT FoFo": 0, "JT Koala": 0, "JT Hana": 0, "JT Rest": 0}, "baronKills": 12, "blueFirstBloodAssistPlayers": {"JT Lilv": 1, "JT Breaker": 1, "JT FoFo": 1, "JT Koala": 2, "JT Hana": 1, "JT Rest": 1}, "firstBloods": 5, "blueMatchesPlayed": 6, "redFirstInhibs": 4, "towerKills": 95, "firstBlueEnemyTowerPosition": {"TOP_LANE": 2, "MID_LANE": 0, "BOT_LANE": 1}}, "DG": {"firstTowerPosition": {"TOP_LANE": 2, "MID_LANE": 1, "BOT_LANE": 4}, "blueDragonKills": 9, "firstBloodPositions": [], "blueBaronKills": 3, "redFirstDeathPlayers": {"DG YuLun": 0, "DG JGY": 2, "DG pasa": 1, "DG 2188": 1, "DG Xiaobo": 0, "DG Moonblack": 0, "DG Soul": 0}, "redFirstBloods": 2, "firstBarons": 1, "redMatchesPlayed": 5, "redTowerKills": 30, "redFirstBloodAssistPlayers": {"DG YuLun": 1, "DG JGY": 1, "DG pasa": 0, "DG 2188": 0, "DG Xiaobo": 0, "DG Moonblack": 0, "DG Soul": 0}, "firstEnemyTowerPosition": {"TOP_LANE": 1, "MID_LANE": 0, "BOT_LANE": 5}, "playersMatchesPlayed": {"DG YuLun": 5, "DG JGY": 13, "DG pasa": 13, "DG 2188": 13, "DG Xiaobo": 8, "DG Moonblack": 10, "DG Soul": 3}, "firstDragons": 7, "redFirstTowers": 3, "dragonKills": 18, "bluePlayersMatchesPlayed": {"DG YuLun": 0, "DG JGY": 0, "DG pasa": 0, "DG 2188": 0, "DG Xiaobo": 0, "DG Moonblack": 0, "DG Soul": 0}, "firstTowers": 7, "blueFirstInhibs": 3, "firstDeathPositions": [], "redFirstBloodPlayers": {"DG YuLun": 0, "DG JGY": 0, "DG pasa": 1, "DG 2188": 0, "DG Xiaobo": 1, "DG Moonblack": 0, "DG Soul": 0}, "redWins": 2, "redDragonKills": 9, "redBaronKills": 2, "redInhibitorKills": 4, "blueFirstDragons": 4, "matchesPlayed": 13, "blueWins": 3, "firstInhibs": 6, "blueFirstBarons": 1, "firstRedTowerPosition": {"TOP_LANE": 1, "MID_LANE": 0, "BOT_LANE": 2}, "totalWins": 5, "blueFirstBloods": 3, "blueTowerKills": 37, "redFirstHeralds": 2, "blueInhibitorKills": 4, "firstDeathPlayers": {"DG YuLun": 0, "DG JGY": 4, "DG pasa": 1, "DG 2188": 1, "DG Xiaobo": 3, "DG Moonblack": 0, "DG Soul": 0}, "firstBloodAssistPlayers": {"DG YuLun": 1, "DG JGY": 3, "DG pasa": 0, "DG 2188": 0, "DG Xiaobo": 0, "DG Moonblack": 1, "DG Soul": 0}, "blueFirstHeralds": 5, "firstBlueTowerPosition": {"TOP_LANE": 1, "MID_LANE": 1, "BOT_LANE": 2}, "firstBloodPlayers": {"DG YuLun": 0, "DG JGY": 1, "DG pasa": 2, "DG 2188": 0, "DG Xiaobo": 1, "DG Moonblack": 1, "DG Soul": 0}, "firstHeralds": 7, "blueFirstBloodPlayers": {"DG YuLun": 0, "DG JGY": 1, "DG pasa": 1, "DG 2188": 0, "DG Xiaobo": 0, "DG Moonblack": 1, "DG Soul": 0}, "blueFirstDeathPlayers": {"DG YuLun": 0, "DG JGY": 2, "DG pasa": 0, "DG 2188": 0, "DG Xiaobo": 3, "DG Moonblack": 0, "DG Soul": 0}, "inhibitorKills": 8, "blueFirstTowers": 4, "redFirstDragons": 3, "redFirstBarons": 0, "firstRedEnemyTowerPosition": {"TOP_LANE": 0, "MID_LANE": 0, "BOT_LANE": 2}, "redPlayersMatchesPlayed": {"DG YuLun": 0, "DG JGY": 0, "DG pasa": 0, "DG 2188": 0, "DG Xiaobo": 0, "DG Moonblack": 0, "DG Soul": 0}, "baronKills": 5, "blueFirstBloodAssistPlayers": {"DG YuLun": 0, "DG JGY": 2, "DG pasa": 0, "DG 2188": 0, "DG Xiaobo": 0, "DG Moonblack": 1, "DG Soul": 0}, "firstBloods": 5, "blueMatchesPlayed": 8, "redFirstInhibs": 3, "towerKills": 67, "firstBlueEnemyTowerPosition": {"TOP_LANE": 1, "MID_LANE": 0, "BOT_LANE": 3}}, "FW": {"firstTowerPosition": {"TOP_LANE": 5, "MID_LANE": 1, "BOT_LANE": 4}, "blueDragonKills": 15, "firstBloodPositions": [], "blueBaronKills": 7, "redFirstDeathPlayers": {"FW Bugi": 1, "FW ShiauC": 2, "FW Hanabi": 1, "FW Rather": 0, "FW Betty": 0}, "redFirstBloods": 4, "firstBarons": 6, "redMatchesPlayed": 8, "redTowerKills": 47, "redFirstBloodAssistPlayers": {"FW Bugi": 3, "FW ShiauC": 1, "FW Hanabi": 0, "FW Rather": 1, "FW Betty": 0}, "firstEnemyTowerPosition": {"TOP_LANE": 1, "MID_LANE": 1, "BOT_LANE": 3}, "playersMatchesPlayed": {"FW Bugi": 15, "FW ShiauC": 15, "FW Hanabi": 15, "FW Rather": 15, "FW Betty": 15}, "firstDragons": 6, "redFirstTowers": 5, "dragonKills": 31, "bluePlayersMatchesPlayed": {"FW Bugi": 0, "FW ShiauC": 0, "FW Hanabi": 0, "FW Rather": 0, "FW Betty": 0}, "firstTowers": 10, "blueFirstInhibs": 6, "firstDeathPositions": [], "redFirstBloodPlayers": {"FW Bugi": 1, "FW ShiauC": 0, "FW Hanabi": 1, "FW Rather": 0, "FW Betty": 2}, "redWins": 4, "redDragonKills": 16, "redBaronKills": 6, "redInhibitorKills": 8, "blueFirstDragons": 4, "matchesPlayed": 15, "blueWins": 6, "firstInhibs": 10, "blueFirstBarons": 6, "firstRedTowerPosition": {"TOP_LANE": 3, "MID_LANE": 1, "BOT_LANE": 1}, "totalWins": 10, "blueFirstBloods": 3, "blueTowerKills": 60, "redFirstHeralds": 4, "blueInhibitorKills": 9, "firstDeathPlayers": {"FW Bugi": 2, "FW ShiauC": 3, "FW Hanabi": 1, "FW Rather": 1, "FW Betty": 1}, "firstBloodAssistPlayers": {"FW Bugi": 5, "FW ShiauC": 3, "FW Hanabi": 0, "FW Rather": 1, "FW Betty": 0}, "blueFirstHeralds": 3, "firstBlueTowerPosition": {"TOP_LANE": 2, "MID_LANE": 0, "BOT_LANE": 3}, "firstBloodPlayers": {"FW Bugi": 1, "FW ShiauC": 0, "FW Hanabi": 2, "FW Rather": 0, "FW Betty": 4}, "firstHeralds": 7, "blueFirstBloodPlayers": {"FW Bugi": 0, "FW ShiauC": 0, "FW Hanabi": 1, "FW Rather": 0, "FW Betty": 2}, "blueFirstDeathPlayers": {"FW Bugi": 1, "FW ShiauC": 1, "FW Hanabi": 0, "FW Rather": 1, "FW Betty": 1}, "inhibitorKills": 17, "blueFirstTowers": 5, "redFirstDragons": 2, "redFirstBarons": 0, "firstRedEnemyTowerPosition": {"TOP_LANE": 0, "MID_LANE": 1, "BOT_LANE": 2}, "redPlayersMatchesPlayed": {"FW Bugi": 0, "FW ShiauC": 0, "FW Hanabi": 0, "FW Rather": 0, "FW Betty": 0}, "baronKills": 13, "blueFirstBloodAssistPlayers": {"FW Bugi": 2, "FW ShiauC": 2, "FW Hanabi": 0, "FW Rather": 0, "FW Betty": 0}, "firstBloods": 7, "blueMatchesPlayed": 7, "redFirstInhibs": 4, "towerKills": 107, "firstBlueEnemyTowerPosition": {"TOP_LANE": 1, "MID_LANE": 0, "BOT_LANE": 1}}, "AHQ": {"firstTowerPosition": {"TOP_LANE": 1, "MID_LANE": 1, "BOT_LANE": 4}, "blueDragonKills": 11, "firstBloodPositions": [], "blueBaronKills": 4, "redFirstDeathPlayers": {"AHQ Baby": 0, "AHQ Wako": 0, "AHQ Ziv": 1, "AHQ An": 1, "AHQ Alex": 0, "AHQ Rainbow": 1, "AHQ Kino": 0}, "redFirstBloods": 4, "firstBarons": 4, "redMatchesPlayed": 7, "redTowerKills": 18, "redFirstBloodAssistPlayers": {"AHQ Baby": 0, "AHQ Wako": 1, "AHQ Ziv": 0, "AHQ An": 0, "AHQ Alex": 0, "AHQ Rainbow": 1, "AHQ Kino": 1}, "firstEnemyTowerPosition": {"TOP_LANE": 3, "MID_LANE": 0, "BOT_LANE": 3}, "playersMatchesPlayed": {"AHQ Baby": 5, "AHQ Wako": 8, "AHQ Ziv": 12, "AHQ An": 12, "AHQ Alex": 7, "AHQ Rainbow": 4, "AHQ Kino": 12}, "firstDragons": 6, "redFirstTowers": 2, "dragonKills": 25, "bluePlayersMatchesPlayed": {"AHQ Baby": 0, "AHQ Wako": 0, "AHQ Ziv": 0, "AHQ An": 0, "AHQ Alex": 0, "AHQ Rainbow": 0, "AHQ Kino": 0}, "firstTowers": 6, "blueFirstInhibs": 3, "firstDeathPositions": [], "redFirstBloodPlayers": {"AHQ Baby": 1, "AHQ Wako": 0, "AHQ Ziv": 0, "AHQ An": 1, "AHQ Alex": 2, "AHQ Rainbow": 0, "AHQ Kino": 0}, "redWins": 0, "redDragonKills": 14, "redBaronKills": 2, "redInhibitorKills": 0, "blueFirstDragons": 4, "matchesPlayed": 12, "blueWins": 3, "firstInhibs": 3, "blueFirstBarons": 4, "firstRedTowerPosition": {"TOP_LANE": 0, "MID_LANE": 0, "BOT_LANE": 2}, "totalWins": 3, "blueFirstBloods": 4, "blueTowerKills": 32, "redFirstHeralds": 2, "blueInhibitorKills": 7, "firstDeathPlayers": {"AHQ Baby": 1, "AHQ Wako": 0, "AHQ Ziv": 1, "AHQ An": 1, "AHQ Alex": 0, "AHQ Rainbow": 1, "AHQ Kino": 0}, "firstBloodAssistPlayers": {"AHQ Baby": 0, "AHQ Wako": 1, "AHQ Ziv": 0, "AHQ An": 2, "AHQ Alex": 1, "AHQ Rainbow": 1, "AHQ Kino": 3}, "blueFirstHeralds": 3, "firstBlueTowerPosition": {"TOP_LANE": 1, "MID_LANE": 1, "BOT_LANE": 2}, "firstBloodPlayers": {"AHQ Baby": 1, "AHQ Wako": 0, "AHQ Ziv": 1, "AHQ An": 2, "AHQ Alex": 3, "AHQ Rainbow": 0, "AHQ Kino": 1}, "firstHeralds": 5, "blueFirstBloodPlayers": {"AHQ Baby": 0, "AHQ Wako": 0, "AHQ Ziv": 1, "AHQ An": 1, "AHQ Alex": 1, "AHQ Rainbow": 0, "AHQ Kino": 1}, "blueFirstDeathPlayers": {"AHQ Baby": 1, "AHQ Wako": 0, "AHQ Ziv": 0, "AHQ An": 0, "AHQ Alex": 0, "AHQ Rainbow": 0, "AHQ Kino": 0}, "inhibitorKills": 7, "blueFirstTowers": 4, "redFirstDragons": 2, "redFirstBarons": 0, "firstRedEnemyTowerPosition": {"TOP_LANE": 2, "MID_LANE": 0, "BOT_LANE": 3}, "redPlayersMatchesPlayed": {"AHQ Baby": 0, "AHQ Wako": 0, "AHQ Ziv": 0, "AHQ An": 0, "AHQ Alex": 0, "AHQ Rainbow": 0, "AHQ Kino": 0}, "baronKills": 6, "blueFirstBloodAssistPlayers": {"AHQ Baby": 0, "AHQ Wako": 0, "AHQ Ziv": 0, "AHQ An": 2, "AHQ Alex": 1, "AHQ Rainbow": 0, "AHQ Kino": 2}, "firstBloods": 8, "blueMatchesPlayed": 5, "redFirstInhibs": 0, "towerKills": 50, "firstBlueEnemyTowerPosition": {"TOP_LANE": 1, "MID_LANE": 0, "BOT_LANE": 0}}}